logging_helper/__init__.py
logging_helper/_metadata.py
logging_helper/logging_helper.py
logging_helper/multi_line_logger.py
logging_helper/unittests/__init__.py
logging_helper/unittests/test_logging_helper.py
logging_helper-1.9.0.dist-info/LICENSE.txt
logging_helper-1.9.0.dist-info/METADATA
logging_helper-1.9.0.dist-info/WHEEL
logging_helper-1.9.0.dist-info/entry_points.txt
logging_helper-1.9.0.dist-info/top_level.txt
logging_helper-1.9.0.dist-info/RECORD
