Metadata-Version: 2.1
Name: logging-helper
Version: 1.9.0
Summary: Provides some enhancements to built-in logging module.
Home-page: https://bitbucket.org/davisowb/logging-helper.git
Author: Oli Davis, Hywel Thomas
Author-email: oli.davis@me.com, hywel.thomas@mac.com
License: MIT
Download-URL: https://bitbucket.org/davisowb/logging-helper.git/get/1.9.0.tar
Keywords: logging
Platform: UNKNOWN
Classifier: Development Status :: 3 - Alpha
Classifier: Intended Audience :: Developers
Classifier: License :: OSI Approved :: MIT License
Classifier: Programming Language :: Python :: 2
Classifier: Programming Language :: Python :: 2.7
Classifier: Programming Language :: Python :: 3
Classifier: Programming Language :: Python :: 3.6
Classifier: Topic :: Utilities
Requires-Dist: pip (>=18.1)
Requires-Dist: better-exceptions (>=0.1.6)
Requires-Dist: logging-tree (>=1.7)
Requires-Dist: future (>=0.16.0)
Provides-Extra: test
Requires-Dist: testfixtures (>=5.4.0) ; extra == 'test'
